{
  "Level": 1,
  "IdentifyName": "GuardUp",
  "Name": "Страж материка",
  "VisionMultiples": {
    "X": 6,
    "Y": 6
  },
  "Size": {
    "X": 1,
    "Y": 1
  },
  "FractionIdentify": "FaithIslandTown",
  "NoInteract": true,
  "NoInteractText": "Страж несёт службу",
  "Face": "Dungeon12.Resources.Images.NPCs.FaithIsland.GuardF.png",
  "Tileset": "Dungeon12.Resources.Images.NPCs.FaithIsland.Guard.png",
  "TileSetRegion": {
    "X": 64,
    "Y": 0,
    "Width": 32,
    "Height": 32
  },
  "MovementSpeed": 0.01,
  "Conversations": [
  ],
  "NPC": {
    "Invulnerable": true,
    "Aggressive": true,
    "WalkChance": 0,
    "Idle": {
      "Tileset": "Dungeon12.Resources.Images.NPCs.FaithIsland.Guard.png",
      "Size": {
        "X": 32,
        "Y": 32
      },
      "Frames": [
        {
          "X": 0,
          "Y": 96
        },
        {
          "X": 32,
          "Y": 96
        },
        {
          "X": 64,
          "Y": 96
        }
      ],
      "Direction": 1
    },
    "MinDMG": 1,
    "MaxDMG": 3,
    "HitPoints": 100,
    "MaxHitPoints": 100
  }
}